GDM-0.8.2.dist-info/DESCRIPTION.rst
GDM-0.8.2.dist-info/METADATA
GDM-0.8.2.dist-info/RECORD
GDM-0.8.2.dist-info/WHEEL
GDM-0.8.2.dist-info/entry_points.txt
GDM-0.8.2.dist-info/metadata.json
GDM-0.8.2.dist-info/top_level.txt
gdm/__init__.py
gdm/cli.py
gdm/commands.py
gdm/common.py
gdm/config.py
gdm/exceptions.py
gdm/git.py
gdm/plugin.py
gdm/settings.py
gdm/shell.py
gdm/source.py
gdm/test/__init__.py
gdm/test/conftest.py
gdm/test/test_cli.py
gdm/test/test_commands.py
gdm/test/test_common.py
gdm/test/test_config.py
gdm/test/test_git.py
gdm/test/test_plugin.py
gdm/test/test_shell.py
gdm/test/test_sources.py
site/__init__.py
tests/__init__.py
tests/conftest.py
tests/test_api.py
tests/test_cli.py
tests/utilities.py
